cscore/__init__.py
cscore/__main__.py
cscore/_logging.py
cscore/grip.py
cscore/imagewriter.py
cscore/version.py
cscore/cvnp/README.md
cscore/cvnp/cvnp.cpp
cscore/cvnp/cvnp.h
cscore/cvnp/cvnp_synonyms.cpp
cscore/cvnp/cvnp_synonyms.h
cscore/src/main.cpp
cscore/_cscore.cp310-win_amd64.lib
cscore/_cscore.cp310-win_amd64.pyd
cscore/_cscore.pyi
cscore/_init__cscore.py
cscore/cscore-casters.pc
cscore/cscore-casters.pybind11.json
cscore/cscore.pc
cscore/trampolines/cs__AxisCamera.hpp
cscore/trampolines/cs__CvSink.hpp
cscore/trampolines/cs__CvSource.hpp
cscore/trampolines/cs__HttpCamera.hpp
cscore/trampolines/cs__ImageSink.hpp
cscore/trampolines/cs__ImageSource.hpp
cscore/trampolines/cs__MjpegServer.hpp
cscore/trampolines/cs__RawEvent.hpp
cscore/trampolines/cs__UsbCamera.hpp
cscore/trampolines/cs__UsbCameraInfo.hpp
cscore/trampolines/cs__VideoCamera.hpp
cscore/trampolines/cs__VideoEvent.hpp
cscore/trampolines/cs__VideoListener.hpp
cscore/trampolines/cs__VideoMode.hpp
cscore/trampolines/cs__VideoProperty.hpp
cscore/trampolines/cs__VideoSink.hpp
cscore/trampolines/cs__VideoSource.hpp
cscore/trampolines/frc__CameraServer.hpp
robotpy_cscore-2025.3.2.3.dist-info/METADATA
robotpy_cscore-2025.3.2.3.dist-info/WHEEL
robotpy_cscore-2025.3.2.3.dist-info/entry_points.txt
robotpy_cscore-2025.3.2.3.dist-info/licenses/LICENSE
robotpy_cscore-2025.3.2.3.dist-info/RECORD
