Metadata-Version: 2.4
Name: robotpy-cscore
Version: 2025.3.2.3
Summary: RobotPy bindings for cscore image processing library
Project-URL: Source code, https://github.com/robotpy/mostrobotpy
Author-email: RobotPy Development Team <robotpy@googlegroups.com>
License-Expression: BSD-3-Clause
License-File: LICENSE
Requires-Dist: pyntcore==2025.3.2.3
Requires-Dist: robotpy-wpinet==2025.3.2.3
Requires-Dist: robotpy-wpiutil==2025.3.2.3
